{"name":"Harmony Brigade","tagline":"mobile app for participants in harmony brigade quartets","body":"# Purpose\r\nThe purpose of this repository is to investigate a [Cordova](http://cordova.apache.org/)-based mobile app to support learning music, particularly for a-cappella singers in [Harmony Brigade](http://http://harmonybrigade.org/)s.\r\n\r\nCurrent targeted platforms include:\r\n- Android\r\n- iOS\r\n- Mac OS X\r\n","google":"UA-2527071-3","note":"Don't delete this file! It's used internally to help with page regeneration."}